elastictalk/__init__.py
elastictalk/pipe/__init__.py
elastictalk/scripts/__init__.py
elastictalk/scripts/elastictalk.py
elastictalk/utils/__init__.py
elastictalk-0.0.1.dist-info/METADATA
elastictalk-0.0.1.dist-info/WHEEL
elastictalk-0.0.1.dist-info/entry_points.txt
elastictalk-0.0.1.dist-info/top_level.txt
elastictalk-0.0.1.dist-info/RECORD
