Metadata-Version: 2.1
Name: elastictalk
Version: 0.0.1
Summary: Extend elastic beanstalk cli tool
Home-page: UNKNOWN
Author: lambdaTW
Author-email: lambda@lambda.tw
License: MIT
Keywords: AWS Elastic Beanstalk
Platform: UNKNOWN
Classifier: Programming Language :: Python :: 3.8
Requires-Dist: awsebcli
Requires-Dist: boto3
Requires-Dist: fire
